LICENSE
dm53/__init__.py
dm53/main.py
dm53/models/domain.py
dm53-0.2.2.dist-info/entry_points.txt
dm53-0.2.2.dist-info/LICENSE
dm53-0.2.2.dist-info/WHEEL
dm53-0.2.2.dist-info/METADATA
dm53-0.2.2.dist-info/RECORD
