Metadata-Version: 2.1
Name: dm53
Version: 0.2.2
Summary: Domain monitoring & registration with AWS route53
Home-page: https://github.com/MousaZeidBaker/dm53
License: MIT
Keywords: domain,monitor,dm53,route53
Author: Mousa Zeid Baker
Requires-Python: >=3.7,<4.0
Classifier: Development Status :: 5 - Production/Stable
Classifier: License :: OSI Approved :: MIT License
Classifier: Operating System :: OS Independent
Classifier: Programming Language :: Python :: 3
Classifier: Programming Language :: Python :: 3.10
Classifier: Programming Language :: Python :: 3.7
Classifier: Programming Language :: Python :: 3.8
Classifier: Programming Language :: Python :: 3.9
Requires-Dist: boto3 (>=1.24.36,<2.0.0)
Requires-Dist: pydantic (>=1.9.1,<2.0.0)
Requires-Dist: typer (>=0.6.1,<0.7.0)
Project-URL: Repository, https://github.com/MousaZeidBaker/dm53
